affinity/__init__.py
affinity/client.py
affinity/compare.py
affinity/downloads.py
affinity/exceptions.py
affinity/filters.py
affinity/hooks.py
affinity/inbound_webhooks.py
affinity/policies.py
affinity/progress.py
affinity/types.py
affinity/cli/__init__.py
affinity/cli/__main__.py
affinity/cli/_update_worker.py
affinity/cli/click_compat.py
affinity/cli/config.py
affinity/cli/constants.py
affinity/cli/context.py
affinity/cli/csv_utils.py
affinity/cli/date_utils.py
affinity/cli/decorators.py
affinity/cli/errors.py
affinity/cli/field_utils.py
affinity/cli/formatters.py
affinity/cli/help_json.py
affinity/cli/interaction_utils.py
affinity/cli/logging.py
affinity/cli/main.py
affinity/cli/mcp_limits.py
affinity/cli/options.py
affinity/cli/paths.py
affinity/cli/progress.py
affinity/cli/render.py
affinity/cli/resolve.py
affinity/cli/resolvers.py
affinity/cli/results.py
affinity/cli/runner.py
affinity/cli/serialization.py
affinity/cli/session_cache.py
affinity/cli/types.py
affinity/cli/update_check.py
affinity/cli/commands/__init__.py
affinity/cli/commands/_entity_files_dump.py
affinity/cli/commands/_entity_files_read.py
affinity/cli/commands/_list_entry_fields.py
affinity/cli/commands/_v1_parsing.py
affinity/cli/commands/company_cmds.py
affinity/cli/commands/completion_cmd.py
affinity/cli/commands/config_cmds.py
affinity/cli/commands/entry_cmds.py
affinity/cli/commands/field_cmds.py
affinity/cli/commands/file_url_cmd.py
affinity/cli/commands/interaction_cmds.py
affinity/cli/commands/list_cmds.py
affinity/cli/commands/note_cmds.py
affinity/cli/commands/opportunity_cmds.py
affinity/cli/commands/person_cmds.py
affinity/cli/commands/query_cmd.py
affinity/cli/commands/relationship_strength_cmds.py
affinity/cli/commands/reminder_cmds.py
affinity/cli/commands/resolve_url_cmd.py
affinity/cli/commands/session_cmds.py
affinity/cli/commands/task_cmds.py
affinity/cli/commands/version_cmd.py
affinity/cli/commands/whoami_cmd.py
affinity/cli/query/__init__.py
affinity_sdk-1.0.1.dist-info/METADATA
affinity_sdk-1.0.1.dist-info/WHEEL
affinity_sdk-1.0.1.dist-info/entry_points.txt
affinity_sdk-1.0.1.dist-info/licenses/LICENSE
affinity_sdk-1.0.1.dist-info/RECORD
