Metadata-Version: 2.4
Name: affinity-sdk
Version: 1.0.1
Summary: A modern, strongly-typed Python SDK for the Affinity CRM API
Project-URL: Homepage, https://github.com/yaniv-golan/affinity-sdk
Project-URL: Documentation, https://yaniv-golan.github.io/affinity-sdk/latest/
Project-URL: Repository, https://github.com/yaniv-golan/affinity-sdk
Project-URL: Issues, https://github.com/yaniv-golan/affinity-sdk/issues
Author: Yaniv Golan
License-Expression: MIT
License-File: LICENSE
Keywords: affinity,api,client,crm,dealflow,relationship-management,sales,sdk
Classifier: Development Status :: 4 - Beta
Classifier: Intended Audience :: Developers
Classifier: License :: OSI Approved :: MIT License
Classifier: Operating System :: OS Independent
Classifier: Programming Language :: Python :: 3
Classifier: Programming Language :: Python :: 3.10
Classifier: Programming Language :: Python :: 3.11
Classifier: Programming Language :: Python :: 3.12
Classifier: Programming Language :: Python :: 3.13
Classifier: Topic :: Office/Business :: Financial :: Investment
Classifier: Topic :: Software Development :: Libraries :: Python Modules
Classifier: Typing :: Typed
Requires-Python: >=3.10
Requires-Dist: httpx<1.0.0,>=0.25.1
Requires-Dist: pydantic<3.0.0,>=2.8.0
Provides-Extra: cli
Requires-Dist: click>=8.1; extra == 'cli'
Requires-Dist: filelock>=3.0; extra == 'cli'
Requires-Dist: packaging>=21.0; extra == 'cli'
Requires-Dist: platformdirs>=4; extra == 'cli'
Requires-Dist: python-dotenv>=1.0.0; extra == 'cli'
Requires-Dist: rich-click>=1.8; extra == 'cli'
Requires-Dist: rich<15,>=13; extra == 'cli'
Requires-Dist: tomli-w>=1.0; extra == 'cli'
Requires-Dist: tomli>=2; (python_version < '3.11') and extra == 'cli'
Provides-Extra: dev
Requires-Dist: click>=8.1; extra == 'dev'
Requires-Dist: filelock>=3.0; extra == 'dev'
Requires-Dist: mypy>=1.10.0; extra == 'dev'
Requires-Dist: packaging>=21.0; extra == 'dev'
Requires-Dist: platformdirs>=4; extra == 'dev'
Requires-Dist: pytest-asyncio>=0.23.0; extra == 'dev'
Requires-Dist: pytest-cov>=4.0.0; extra == 'dev'
Requires-Dist: pytest>=8.0.0; extra == 'dev'
Requires-Dist: respx>=0.21.0; extra == 'dev'
Requires-Dist: rich-click>=1.8; extra == 'dev'
Requires-Dist: rich<15,>=13; extra == 'dev'
Requires-Dist: ruff>=0.5.0; extra == 'dev'
Requires-Dist: tomli>=2; extra == 'dev'
Provides-Extra: docs
Requires-Dist: mike>=2.0.0; extra == 'docs'
Requires-Dist: mkdocs-include-markdown-plugin>=7.0.0; extra == 'docs'
Requires-Dist: mkdocs-material>=9.0.0; extra == 'docs'
Requires-Dist: mkdocs>=1.5.0; extra == 'docs'
Requires-Dist: mkdocstrings[python]>=0.24.0; extra == 'docs'
Provides-Extra: dotenv
Requires-Dist: python-dotenv>=1.0.0; extra == 'dotenv'
